[{"name":"hast","paname":{ "Регіональний ландшафтний парк «Сокольники-Помірки»" : "448012718", "Ботанічна пам'ятка природи «Інститутська»" : "360601180", "Ботанічна пам'ятка природи місцевого значення «Сокольники-Помірки»" : "448012718", "Регіональний ландшафтний парк «Сокольники-Помірки»" : "360601313" },"count":5389},{"name":"a_biatov","paname":{ "Ботанічна пам'ятка природи місцевого значення «Сокольники-Помірки»" : "448012718", "Регіональний ландшафтний парк «Сокольники-Помірки»" : "360601313", "Національний природний парк «Слобожанський»" : "-3419143" },"count":1583},{"name":"approksimator","paname":{ "бульвар" : "256474904", "бульвар" : "444883195", "Національний природний парк «Голосіївський»" : "-1652168" },"count":604},{"name":"svetlulichka","paname":{ "Protected Area" : "23709110", "Національний природний парк «Голосіївський»" : "-1652168" },"count":196}]
